cchoir/__init__.py
cchoir/cli.py
cchoir/commands/__init__.py
cchoir/commands/command.py
cchoir/commands/deploy.py
cchoir-0.0.1.dist-info/LICENSE
cchoir-0.0.1.dist-info/METADATA
cchoir-0.0.1.dist-info/WHEEL
cchoir-0.0.1.dist-info/entry_points.txt
cchoir-0.0.1.dist-info/top_level.txt
cchoir-0.0.1.dist-info/RECORD
